sideral/__init__.py
sideral/command.py
sideral/errors.py
sideral/loader.py
sideral/persister.py
sideral/proxy.py
sideral/repository.py
sideral/result.py
sideral/schema.py
sideral/session.py
sideral/strategy.py
sideral/utils.py
sideral/annotation/__init__.py
sideral/annotation/annotations.py
sideral/annotation/column.py
sideral/annotation/override.py
sideral/annotation/private_list.py
sideral/annotation/relationships.py
sideral/annotation/utils.py
sideral/event/__init__.py
sideral/event/events.py
sideral/event/listeners.py
sideral/mapper/__init__.py
sideral/mapper/model.py
sideral/mapper/properties.py
sideral/query/__init__.py
sideral/query/builder.py
sideral/query/condition.py
sideral/query/interfaces.py
sideral/query/utils.py
sideral-0.0.3.dist-info/LICENSE
sideral-0.0.3.dist-info/METADATA
sideral-0.0.3.dist-info/WHEEL
sideral-0.0.3.dist-info/top_level.txt
sideral-0.0.3.dist-info/RECORD
